{
  "miniapp": {
    "version": "1",
    "name": "CAMPUS",
    "iconUrl": "https://base-batches-miniapp-cc.vercel.app/CampusCoin.png",
    "homeUrl": "https://base-batches-miniapp-cc.vercel.app/",
    "splashImageUrl": "https://base-batches-miniapp-cc.vercel.app/CampusCoin.png",
    "splashBackgroundColor": "#0A0A0A",
    "subtitle": "Marketplace universitario global",
    "description": "Tu marketplace universitario global - Compra, vende y gana tokens $CAMPUS",
    "primaryCategory": "shopping",
    "tags": [
      "marketplace",
      "universidad",
      "tokens",
      "blockchain",
      "estudiantes"
    ],
    "heroImageUrl": "https://base-batches-miniapp-cc.vercel.app/CampusCoin.png",
    "tagline": "Marketplace universitario global",
    "ogTitle": "CAMPUS",
    "ogDescription": "Tu marketplace universitario global - Compra, vende y gana tokens $CAMPUS",
    "ogImageUrl": "https://base-batches-miniapp-cc.vercel.app/CampusCoin.png",
    "requiredChains": [
      "eip155:8453"
    ],
    "requiredCapabilities": [
      "actions.signIn",
      "wallet.getEthereumProvider"
    ]
  }
}